[
  {
    "id": "decoration-16",
    "caption": "Carolina Experience",
    "url": "/decoration/Diwali Sparkle Experience (1).jpg"
  },
  {
    "id": "decoration-1",
    "caption": "Carolina Evening Dining Reservation",
    "url": "/decoration/Carolina Evening Dining Reservation.webp"
  },
  {
    "id": "decoration-2",
    "caption": "Carolina Hall Atmosphere",
    "url": "/decoration/Carolina Experience Details Atmosphere.jpg"
  },
  {
    "id": "decoration-3",
    "caption": "Carolina Celebration Look",
    "url": "/decoration/Carolina Lo Celebration.jpg"
  },
  {
    "id": "decoration-14",
    "caption": "Dine in Perfection",
    "url": "/decoration/Dine in Perfection.jpg"
  },
  {
    "id": "decoration-4",
    "caption": "Carolina Lounge Style",
    "url": "/decoration/Carolina Lounge Style (1).jpg"
  },
  {
    "id": "decoration-23",
    "caption": "Golden Evenings Rooftop Vibes",
    "url": "/decoration/Golden Evenings Rooftop Vibes (1).jpg"
  },
  {
    "id": "decoration-10",
    "caption": "Carolina Table Booking",
    "url": "/decoration/Carolina Table Booking (1).jpg"
  },
  {
    "id": "decoration-13",
    "caption": "Chef at Work",
    "url": "/decoration/Chef at Work.jpg"
  },
  {
    "id": "decoration-15",
    "caption": "Dining Ambiance",
    "url": "/decoration/Dining Ambiance.jpg"
  },
  {
    "id": "decoration-24",
    "caption": "Perfect Setting Moments",
    "url": "/decoration/Perfect Setting Moments.jpg"
  },
  {
    "id": "decoration-25",
    "caption": "Soft Lights Artistic Walls Cozy Corner",
    "url": "/decoration/Soft Lights Artistic Walls Cozy Corner.jpg"
  }
]